Metadata-Version: 2.1
Name: utm-no-numpy
Version: 0.7.2.11
Summary: Bidirectional UTM-WGS84 converter for python
Home-page: https://github.com/JamesParrott/utm-no-numpy
Author: Tobias Bieniek
Author-email: none@example.com
License: UNKNOWN
Keywords: utm,wgs84,coordinate,converter
Platform: UNKNOWN
Classifier: Programming Language :: Python
Classifier: License :: OSI Approved :: MIT License
Classifier: Operating System :: OS Independent
Classifier: Development Status :: 4 - Beta
Classifier: Environment :: Other Environment
Classifier: Intended Audience :: Developers
Classifier: Intended Audience :: Science/Research
Classifier: Topic :: Scientific/Engineering :: GIS
License-File: LICENSE
